neural_network_kpp/__init__.py
neural_network_kpp/activations.py
neural_network_kpp/layers.py
neural_network_kpp/losses.py
neural_network_kpp/network.py
neural_network_kpp/train.py
neural_network_kkp-0.0.7.9.dist-info/METADATA
neural_network_kkp-0.0.7.9.dist-info/WHEEL
neural_network_kkp-0.0.7.9.dist-info/top_level.txt
neural_network_kkp-0.0.7.9.dist-info/RECORD
