Metadata-Version: 2.1
Name: neural_network_kkp
Version: 0.0.7.9
Summary: Простая библиотека для полносвязных нейронных сетей
Author: Тихонов Иван
Author-email: tihonovivan737@gmail.com
Requires-Python: >=3.6
Requires-Dist: numpy
